pplkit/__init__.py
pplkit/data/__init__.py
pplkit/data/interface.py
pplkit/data/io.py
pplkit-0.1.0.dist-info/LICENSE
pplkit-0.1.0.dist-info/METADATA
pplkit-0.1.0.dist-info/WHEEL
pplkit-0.1.0.dist-info/top_level.txt
pplkit-0.1.0.dist-info/RECORD
