Metadata-Version: 2.1
Name: pplkit
Version: 0.1.0
Summary: Pipeline building toolkit
Author-email: IHME Math Sciences <ihme.math.sciences@gmail.com>
License: BSD 2-Clause License
Project-URL: github, https://github.com/ihmeuw-msca/pplkit
Requires-Python: >=3.10
License-File: LICENSE
Requires-Dist: dill
Requires-Dist: pyyaml
Requires-Dist: pandas[parquet]
Requires-Dist: tomli
Requires-Dist: tomli-w
Provides-Extra: docs
Requires-Dist: sphinx ; extra == 'docs'
Requires-Dist: sphinx-autodoc-typehints ; extra == 'docs'
Requires-Dist: furo ; extra == 'docs'
Provides-Extra: test
Requires-Dist: pytest ; extra == 'test'
